[
    {
        "url" : "https://dynamic-media-cdn.tripadvisor.com/media/photo-o/17/3a/50/bd/photo0jpg.jpg?w=1200&h=1200&s=1",
        "type" : "Image",
        "date" : "DD/MM/YYYY",
        "auteur" : "Auteur",
        "titre" : "Titre",
        "lier" : {
            "concert" : [],
            "artiste" : [],
            "groupe" : [],
            "soiree" : [],
            "salle" : [
                "1"
            ]
        }
    },
    {
        "url" : "https://www.brest.fr/fileadmin/imported_for_brest/fileadmin/Images/Au_quotidien/Bouger_se_divertir/Culture/Equipements_culturels/capucins/DL_MLG_DSC_7047.jpg",
        "type" : "Image",
        "date" : "DD/MM/YYYY",
        "auteur" : "Auteur",
        "titre" : "Titre",
        "lier" : {
            "concert" : [],
            "artiste" : [],
            "groupe" : [],
            "soiree" : [],
            "salle" : [
                "1"
            ]
        }
    },
    {
        "url" : "https://weezevent.com/wp-content/uploads/2018/08/27184142/organiser-un-concert-en-7-etapes.png",
        "type" : "Image",
        "date" : "DD/MM/YYYY",
        "auteur" : "Auteur",
        "titre" : "Titre",
        "lier" : {
            "concert" : [
                "1"
            ],
            "artiste" : [],
            "groupe" : [],
            "soiree" : [],
            "salle" : []
        }
    },
    {
        "url" : "https://www.francebleu.fr/s3/cruiser-production/2020/03/276fc218-fe5b-415b-8ef8-3a6d9e9c1637/1200x680_myspace-musique.jpg",
        "type" : "Image",
        "date" : "DD/MM/YYYY",
        "auteur" : "Auteur",
        "titre" : "Titre",
        "lier" : {
            "concert" : [],
            "artiste" : [
                "1",
                "2"
            ],
            "groupe" : [],
            "soiree" : [],
            "salle" : []
        }
    },
    {
        "url" : "https://www.senscritique.com/liste/Top_Artiste_Musique/1232129",
        "type" : "Article",
        "date" : "DD/MM/YYYY",
        "auteur" : "Auteur",
        "titre" : "Titre",
        "lier" : {
            "concert" : [],
            "artiste" : [
                "1"
            ],
            "groupe" : [],
            "soiree" : [],
            "salle" : []
        }
    },
    {
        "url" : "https://www.senscritique.com/liste/Top_Artiste_Musique/1232129",
        "type" : "Article",
        "date" : "DD/MM/YYYY",
        "auteur" : "Auteur",
        "titre" : "Titre",
        "lier" : {
            "concert" : [],
            "artiste" : [],
            "groupe" : [],
            "soiree" : [],
            "salle" : [
                "1"
            ]
        }
    }
]